mysql_to_obsidian_bases/__init__.py
mysql_to_obsidian_bases/__main__.py
mysql_to_obsidian_bases/base_generator.py
mysql_to_obsidian_bases/cli.py
mysql_to_obsidian_bases/markdown_generator.py
mysql_to_obsidian_bases/mysql_utils.py
mysql_to_obsidian_bases/type_inference.py
mysql_to_obsidian_bases-0.1.1.dist-info/licenses/LICENSE
mysql_to_obsidian_bases-0.1.1.dist-info/METADATA
mysql_to_obsidian_bases-0.1.1.dist-info/WHEEL
mysql_to_obsidian_bases-0.1.1.dist-info/entry_points.txt
mysql_to_obsidian_bases-0.1.1.dist-info/top_level.txt
mysql_to_obsidian_bases-0.1.1.dist-info/RECORD
