Metadata-Version: 2.4
Name: mysql-to-obsidian-bases
Version: 0.1.1
Summary: Convert MySQL tables into Obsidian notes and Bases .base files
Author: Olle
License:                                  Apache License
Project-URL: Homepage, https://github.com/astrooom/mysql-to-obsidian-bases
Project-URL: Repository, https://github.com/astrooom/mysql-to-obsidian-bases
Project-URL: Issues, https://github.com/astrooom/mysql-to-obsidian-bases/issues
Keywords: obsidian,bases,mysql,markdown,export,cli
Classifier: Development Status :: 3 - Alpha
Classifier: Intended Audience :: End Users/Desktop
Classifier: License :: OSI Approved :: MIT License
Classifier: Programming Language :: Python
Classifier: Programming Language :: Python :: 3
Classifier: Programming Language :: Python :: 3 :: Only
Classifier: Programming Language :: Python :: 3.9
Classifier: Programming Language :: Python :: 3.10
Classifier: Programming Language :: Python :: 3.11
Classifier: Programming Language :: Python :: 3.12
Classifier: Environment :: Console
Classifier: Topic :: Utilities
Requires-Python: >=3.9
License-File: LICENSE
Requires-Dist: mysql-connector-python>=8.3
Requires-Dist: PyYAML>=6.0
Dynamic: license-file
